LICENSE-MIT
MANIFEST.in
README.md
setup.py
cms_bootstrap/__init__.py
cms_bootstrap/models.py
cms_bootstrap/static/cms_bootstrap/js/ng-nav-navbar.js
cms_bootstrap/templates/bootstrap3/components/paginator.html
cms_bootstrap/templates/bootstrap3/includes/breadcrumb-row.html
cms_bootstrap/templates/bootstrap3/includes/language-chooser.html
cms_bootstrap/templates/bootstrap3/includes/nav-navbar.html
cms_bootstrap/templates/bootstrap3/includes/nav-secondary.html
cms_bootstrap/templates/bootstrap3/includes/ng-nav-navbar.html
cms_bootstrap/templates/bootstrap3/menu/breadcrumb.html
cms_bootstrap/templates/bootstrap3/menu/navbar.html
cms_bootstrap/templates/bootstrap3/menu/ng-navbar.html
cms_bootstrap/templates/bootstrap4/components/menu-icon.html
cms_bootstrap/templates/bootstrap4/components/paginator.html
cms_bootstrap/templates/bootstrap4/includes/language-chooser.html
cms_bootstrap/templates/bootstrap4/includes/nav-breadcrumb.html
cms_bootstrap/templates/bootstrap4/includes/nav-navbar.html
cms_bootstrap/templates/bootstrap4/includes/nav-secondary.html
cms_bootstrap/templates/bootstrap4/includes/ng-language-chooser.html
cms_bootstrap/templates/bootstrap4/includes/ng-nav-navbar.html
cms_bootstrap/templates/bootstrap4/menu/breadcrumb.html
cms_bootstrap/templates/bootstrap4/menu/navbar.html
cms_bootstrap/templates/bootstrap4/menu/ng-navbar.html
cms_bootstrap/templatetags/__init__.py
cms_bootstrap/templatetags/bootstrap_tags.py
djangocms_bootstrap.egg-info/PKG-INFO
djangocms_bootstrap.egg-info/SOURCES.txt
djangocms_bootstrap.egg-info/dependency_links.txt
djangocms_bootstrap.egg-info/not-zip-safe
djangocms_bootstrap.egg-info/requires.txt
djangocms_bootstrap.egg-info/top_level.txt