Metadata-Version: 2.1
Name: djangocms-bootstrap
Version: 1.1.1
Summary: Templates and templatetags to be used with django-CMS with Bootstrap3 or Bootstrap4.
Home-page: https://github.com/jrief/djangocms-bootstrap
Author: Jacob Rief
Author-email: jacob.rief@gmail.com
License: MIT
Keywords: django-cms,bootstrap-3,bootstrap-4
Platform: OS Independent
Classifier: Development Status :: 4 - Beta
Classifier: Environment :: Web Environment
Classifier: Framework :: Django
Classifier: Intended Audience :: Developers
Classifier: License :: OSI Approved :: MIT License
Classifier: Operating System :: OS Independent
Classifier: Programming Language :: Python
Classifier: Topic :: Internet :: WWW/HTTP :: Dynamic Content
Classifier: Programming Language :: Python :: 2.7
Classifier: Programming Language :: Python :: 3.4
Classifier: Programming Language :: Python :: 3.5
Classifier: Programming Language :: Python :: 3.6
Classifier: Framework :: Django :: 1.10
Classifier: Framework :: Django :: 1.11
Classifier: Framework :: Django :: 2.0
Classifier: Framework :: Django :: 2.1
